setup.py
heamon7_tushare.egg-info/PKG-INFO
heamon7_tushare.egg-info/SOURCES.txt
heamon7_tushare.egg-info/dependency_links.txt
heamon7_tushare.egg-info/top_level.txt
tushare/__init__.py
tushare/data/__init__.py
tushare/datayes/HKequity.py
tushare/datayes/IV.py
tushare/datayes/__init__.py
tushare/datayes/api.py
tushare/datayes/bond.py
tushare/datayes/equity.py
tushare/datayes/fund.py
tushare/datayes/fundamental.py
tushare/datayes/future.py
tushare/datayes/idx.py
tushare/datayes/macro.py
tushare/datayes/market.py
tushare/datayes/master.py
tushare/datayes/options.py
tushare/datayes/subject.py
tushare/fund/__init__.py
tushare/fund/cons.py
tushare/fund/nav.py
tushare/futures/__init__.py
tushare/futures/cons.py
tushare/futures/intlfutures.py
tushare/internet/__init__.py
tushare/internet/boxoffice.py
tushare/stock/__init__.py
tushare/stock/billboard.py
tushare/stock/classifying.py
tushare/stock/cons.py
tushare/stock/fundamental.py
tushare/stock/globals.py
tushare/stock/macro.py
tushare/stock/macro_vars.py
tushare/stock/news_vars.py
tushare/stock/newsevent.py
tushare/stock/ref_vars.py
tushare/stock/reference.py
tushare/stock/shibor.py
tushare/stock/trading.py
tushare/trader/__init__.py
tushare/trader/trader.py
tushare/trader/utils.py
tushare/trader/vars.py
tushare/util/__init__.py
tushare/util/common.py
tushare/util/dateu.py
tushare/util/netbase.py
tushare/util/store.py
tushare/util/upass.py
tushare/util/vars.py