Metadata-Version: 1.1
Name: heamon7-tushare
Version: 0.1.0
Summary: A utility for crawling historical and Real-time Quotes data of China stocks
Home-page: http://tushare.org
Author: Jimmy Liu
Author-email: jimmysoa@sina.cn
License: BSD
Keywords: China stock data
Platform: UNKNOWN
Classifier: Development Status :: 4 - Beta
Classifier: Programming Language :: Python :: 2.6
Classifier: Programming Language :: Python :: 2.7
Classifier: Programming Language :: Python :: 3.2
Classifier: Programming Language :: Python :: 3.3
Classifier: Programming Language :: Python :: 3.4
Classifier: License :: OSI Approved :: BSD License
